README.rst
setup.py
devilsmachine/__init__.py
devilsmachine/__main__.py
devilsmachine/colladaparser.py
devilsmachine/data.py
devilsmachine/filebuilder.py
devilsmachine/vertex.py
devilsmachine.egg-info/PKG-INFO
devilsmachine.egg-info/SOURCES.txt
devilsmachine.egg-info/dependency_links.txt
devilsmachine.egg-info/requires.txt
devilsmachine.egg-info/top_level.txt