Metadata-Version: 1.1
Name: devilsmachine
Version: 0.1.0
Summary: A content processor
Home-page: https://github.com/galaxgames/devilsmachine
Author: Sam Fuller
Author-email: sam@samfullerstudios.com
License: Apache
Keywords: development build-tools
Platform: UNKNOWN
Classifier: Development Status :: 2 - Pre-Alpha
Classifier: Intended Audience :: Developers
Classifier: Topic :: Software Development :: Build Tools
Classifier: License :: OSI Approved :: Apache Software License
Classifier: Programming Language :: Python :: 3.5
